datatableview_user_columns/__init__.py
datatableview_user_columns/datatables.py
datatableview_user_columns/forms.py
datatableview_user_columns/models.py
datatableview_user_columns/urls.py
datatableview_user_columns/views.py
datatableview_user_columns/migrations/0001_initial.py
datatableview_user_columns/migrations/0002_auto_20210722_2316.py
datatableview_user_columns/migrations/__init__.py
datatableview_user_columns/static/css/selectize.css
datatableview_user_columns/static/css/selectize.min.css
datatableview_user_columns/static/js/selectize.js
datatableview_user_columns/static/js/selectize.min.js
datatableview_user_columns/templates/datatableview_user_columns/datatableusercolumns_form.html
datatableview_user_columns/templates/datatableview_user_columns/datatableusercolumns_list.html
datatableview_user_columns-1.2.3.dist-info/LICENSE.txt
datatableview_user_columns-1.2.3.dist-info/METADATA
datatableview_user_columns-1.2.3.dist-info/WHEEL
datatableview_user_columns-1.2.3.dist-info/top_level.txt
datatableview_user_columns-1.2.3.dist-info/RECORD
