Metadata-Version: 2.1
Name: datatableview-user-columns
Version: 1.2.3
Summary: Allows a user to specify columns for a datatableview
Home-page: https://github.com/icmanage/django-datatable-view-user-columns
Author: Steven Klass
Author-email: sklass@icmanage.com
License: UNKNOWN
Download-URL: https://github.com/icmanage/django-datatable-view-user-columns/archive/1.2.3.tar.gz
Project-URL: Bug Reports, https://github.com/icmanage/django-datatable-view-user-columns/issues
Project-URL: Say Thanks!, http://saythanks.io/to/rh0dium
Project-URL: Source, https://github.com/icmanage/django-datatable-view-user-columns
Keywords: django datatableview
Platform: UNKNOWN
Classifier: Development Status :: 4 - Beta
Classifier: Environment :: Web Environment
Classifier: Framework :: Django
Classifier: License :: OSI Approved :: MIT License
Classifier: Programming Language :: Python :: 3
Classifier: Programming Language :: Python :: 3.7
Classifier: Programming Language :: Python :: 3.8
Classifier: Programming Language :: Python :: 3.9
License-File: LICENSE.txt
Requires-Dist: django (<4.0,>=3)
Requires-Dist: django-datatable-view
